huscy/project_design/__init__.py
huscy/project_design/admin.py
huscy/project_design/apps.py
huscy/project_design/models.py
huscy/project_design/permissions.py
huscy/project_design/serializer.py
huscy/project_design/services.py
huscy/project_design/urls.py
huscy/project_design/views.py
huscy/project_design/migrations/0001_initial.py
huscy/project_design/migrations/__init__.py
huscy_project_design-1.1.0.dist-info/METADATA
huscy_project_design-1.1.0.dist-info/WHEEL
huscy_project_design-1.1.0.dist-info/licenses/LICENSE
huscy_project_design-1.1.0.dist-info/RECORD
