Metadata-Version: 2.4
Name: huscy.project_design
Version: 1.1.0
Summary: Defining a project design for projects in a research context.
Project-URL: homepage, https://bitbucket.org/huscy/project_design
Author-email: Stefan Bunde <stefanbunde+git@posteo.de>
License-Expression: AGPL-3.0-or-later
License-File: LICENSE
Classifier: Development Status :: 5 - Production/Stable
Classifier: Framework :: Django
Classifier: Framework :: Django :: 4.2
Classifier: Framework :: Django :: 5.1
Classifier: Framework :: Django :: 5.2
Classifier: License :: OSI Approved :: GNU Affero General Public License v3 or later (AGPLv3+)
Classifier: Operating System :: OS Independent
Classifier: Programming Language :: Python
Classifier: Programming Language :: Python :: 3
Classifier: Programming Language :: Python :: 3 :: Only
Classifier: Programming Language :: Python :: 3.9
Classifier: Programming Language :: Python :: 3.10
Classifier: Programming Language :: Python :: 3.11
Classifier: Programming Language :: Python :: 3.12
Classifier: Programming Language :: Python :: 3.13
Requires-Dist: huscy-projects
Requires-Dist: huscy-users
Provides-Extra: development
Requires-Dist: psycopg2-binary; extra == 'development'
Provides-Extra: testing
Requires-Dist: tox; extra == 'testing'
Requires-Dist: watchdog; extra == 'testing'
